re2.py
_re2.cpython-37m-x86_64-linux-gnu.so
.libs_re2/libre2-c9958724.so.0.0.0
fb_re2_wheels-1.0.7.dist-info/METADATA
fb_re2_wheels-1.0.7.dist-info/RECORD
fb_re2_wheels-1.0.7.dist-info/WHEEL
fb_re2_wheels-1.0.7.dist-info/top_level.txt
