Metadata-Version: 2.1
Name: fb-re2-wheels
Version: 1.0.7
Summary: Manylinux wheel for a Python wrapper for Google's RE2
Home-page: UNKNOWN
Author: UNKNOWN
Author-email: UNKNOWN
License: UNKNOWN
Platform: UNKNOWN
Classifier: Intended Audience :: Developers
Classifier: License :: OSI Approved :: BSD License
Classifier: Development Status :: 5 - Production/Stable
